LICENSE
setup.py
oracle_graph_client.egg-info/PKG-INFO
oracle_graph_client.egg-info/SOURCES.txt
oracle_graph_client.egg-info/dependency_links.txt
oracle_graph_client.egg-info/requires.txt
oracle_graph_client.egg-info/top_level.txt
python/opg4py/__init__.py
python/opg4py/adb.py
python/opg4py/graph_server.py
python/opg4py/_adb/__init__.py
python/opg4py/_adb/job.py
python/opg4py/_utils/__init__.py
python/opg4py/_utils/env_vars.py
python/opg4py/_utils/error_handling.py
python/opg4py/_utils/item_converter.py
python/opg4py/graph_importer/__init__.py
python/opg4py/graph_importer/_graph_importer.py
python/opg4py/jars/algorithm.api-0.1.2-20241129.jar
python/opg4py/jars/aopalliance-1.0.jar
python/opg4py/jars/capsule-0.6.3.jar
python/opg4py/jars/commons-io-2.16.1.jar
python/opg4py/jars/commons-lang3-3.18.0.jar
python/opg4py/jars/commons-logging-1.3.4.jar
python/opg4py/jars/commons-vfs2-2.10.0.jar
python/opg4py/jars/failureaccess-1.0.2.jar
python/opg4py/jars/fastdoubleparser-1.0.0.jar
python/opg4py/jars/fastutil-8.5.15.jar
python/opg4py/jars/graph-query-ir-2.1.0.3.jar
python/opg4py/jars/guava-33.4.0-jre.jar
python/opg4py/jars/guice-6.0.0.jar
python/opg4py/jars/gvt-driver-25.4.2.jar
python/opg4py/jars/gvt-formatter-25.4.2.jar
python/opg4py/jars/gvt-library-25.4.2.jar
python/opg4py/jars/gvt-pgql-driver-25.4.2.jar
python/opg4py/jars/gvt-pgx-driver-25.4.2.jar
python/opg4py/jars/gvt-rdbms-driver-25.4.2.jar
python/opg4py/jars/gvt-rest-25.4.2.jar
python/opg4py/jars/httpclient5-5.4.4.jar
python/opg4py/jars/httpclient5-fluent-5.4.4.jar
python/opg4py/jars/httpcore5-5.3.4.jar
python/opg4py/jars/httpcore5-h2-5.3.4.jar
python/opg4py/jars/jackson-annotations-2.17.1.jar
python/opg4py/jars/jackson-core-2.17.1.jar
python/opg4py/jars/jackson-databind-2.17.1.jar
python/opg4py/jars/jakarta.inject-api-2.0.1.jar
python/opg4py/jars/javax.activation-api-1.2.0.jar
python/opg4py/jars/javax.annotation-api-1.3.2.jar
python/opg4py/jars/javax.inject-1.jar
python/opg4py/jars/javax.servlet-api-4.0.1.jar
python/opg4py/jars/javax.ws.rs-api-2.1.1.jar
python/opg4py/jars/jaxb-api-2.3.1.jar
python/opg4py/jars/json-sanitizer-1.2.3.jar
python/opg4py/jars/jsr305-3.0.2.jar
