Metadata-Version: 2.1
Name: oracle-graph-client
Version: 25.4.0
Summary: Oracle Graph Python Client
Home-page: https://www.oracle.com/database/graph/
License: Oracle Free Use Terms and Conditions (FUTC)
Platform: Linux x86_64
Requires-Python: >=3.10
License-File: LICENSE
